{
  "label": "KeyVault investor dashboard daily stamp",
  "schedule": "Daily at 5:00 PM America/New_York",
  "stampedAt": "2026-05-14T21:57:08.537Z",
  "stampedAtEastern": "May 14, 2026, 5:57 PM EDT",
  "sourceReportUrl": "https://app.primenumber.trade/data/jlp_report.html",
  "sourceReportLastUpdated": "May 14, 2026",
  "strategy": "3x JLP (borrow SOL) + Aster Funding",
  "summary": {
    "strategy": "3x JLP (borrow SOL) + Aster Funding",
    "startDate": "2025-11-06",
    "endDate": "2026-05-14",
    "cumulative": 13.6,
    "annualized": 26.12,
    "sevenDayRollingApy": 16.78,
    "thirtyDayRollingApy": 12.41,
    "ninetyDayRollingApy": 20.61
  }
}
