{
  "snapshots": [
    {
      "timestamp": "2026-02-09T14:00:04.921Z",
      "date": "2026-02-09",
      "navPrice": 3.657352,
      "aum": 1167906609.614972,
      "jupiterApyPct": 52.48,
      "fees24h": 952780,
      "avgDailyFees7d": 3513789,
      "realTimeFeeApyPct": 82.36,
      "traderExposure": {
        "SOL": {
          "guaranteedUsd": 18985732.550466,
          "globalShortSizes": 7872534.436115,
          "shortPnlDelta": 338147.69193,
          "shortTradersHasProfit": true,
          "netPnl": 338147.69193
        },
        "ETH": {
          "guaranteedUsd": 1311300.745445,
          "globalShortSizes": 1659363.432109,
          "shortPnlDelta": 66143.471875,
          "shortTradersHasProfit": true,
          "netPnl": 66143.471875
        },
        "WBTC": {
          "guaranteedUsd": 8213579.597633,
          "globalShortSizes": 5743524.559926,
          "shortPnlDelta": 271061.367319,
          "shortTradersHasProfit": true,
          "netPnl": 271061.367319
        }
      },
      "totalTraderPnl": 675352.53,
      "traderPnlLabel": "traders_winning"
    },
    {
      "timestamp": "2026-02-11T14:00:06.452Z",
      "date": "2026-02-11",
      "navPrice": 3.603332,
      "aum": 1188504641.072553,
      "jupiterApyPct": 52.48,
      "fees24h": 1029282,
      "avgDailyFees7d": 3235197,
      "realTimeFeeApyPct": 74.52,
      "traderExposure": {
        "SOL": {
          "guaranteedUsd": 20091317.777652,
          "globalShortSizes": 9807757.224744,
          "shortPnlDelta": 387592.136974,
          "shortTradersHasProfit": true,
          "netPnl": 387592.136974
        },
        "ETH": {
          "guaranteedUsd": 1787848.79673,
          "globalShortSizes": 3079386.824427,
          "shortPnlDelta": 139180.037238,
          "shortTradersHasProfit": true,
          "netPnl": 139180.037238
        },
        "WBTC": {
          "guaranteedUsd": 9069874.504528,
          "globalShortSizes": 6209359.649387,
          "shortPnlDelta": 312629.303859,
          "shortTradersHasProfit": true,
          "netPnl": 312629.303859
        }
      },
      "totalTraderPnl": 839401.48,
      "traderPnlLabel": "traders_winning"
    },
    {
      "timestamp": "2026-02-12T22:10:08.137Z",
      "date": "2026-02-12",
      "navPrice": 3.500895,
      "aum": 1152891515.107671,
      "jupiterApyPct": 52.48,
      "fees24h": 1611157,
      "avgDailyFees7d": 2912570,
      "realTimeFeeApyPct": 69.16,
      "traderExposure": {
        "SOL": {
          "guaranteedUsd": 19701196.007183,
          "globalShortSizes": 11048689.522767,
          "shortPnlDelta": 677525.392547,
          "shortTradersHasProfit": true,
          "netPnl": 677525.392547
        },
        "ETH": {
          "guaranteedUsd": 3539766.726765,
          "globalShortSizes": 1542820.951892,
          "shortPnlDelta": 62070.489741,
          "shortTradersHasProfit": true,
          "netPnl": 62070.489741
        },
        "WBTC": {
          "guaranteedUsd": 9725427.700327,
          "globalShortSizes": 6766059.178292,
          "shortPnlDelta": 371598.797561,
          "shortTradersHasProfit": true,
          "netPnl": 371598.797561
        }
      },
      "totalTraderPnl": 1111194.68,
      "traderPnlLabel": "traders_winning"
    },
    {
      "timestamp": "2026-02-13T14:00:05.323Z",
      "date": "2026-02-13",
      "navPrice": 3.577133,
      "aum": 1175269486.860552,
      "jupiterApyPct": 52.48,
      "fees24h": 1210840,
      "avgDailyFees7d": 2050150,
      "realTimeFeeApyPct": 47.75,
      "traderExposure": {
        "SOL": {
          "guaranteedUsd": 17228632.394089,
          "globalShortSizes": 15544240.662287,
          "shortPnlDelta": 293310.46843,
          "shortTradersHasProfit": true,
          "netPnl": 293310.46843
        },
        "ETH": {
          "guaranteedUsd": 1709075.909143,
          "globalShortSizes": 1756828.815457,
          "shortPnlDelta": 27976.431829,
          "shortTradersHasProfit": true,
          "netPnl": 27976.431829
        },
        "WBTC": {
          "guaranteedUsd": 9455107.728736,
          "globalShortSizes": 6754535.095032,
          "shortPnlDelta": 239314.618574,
          "shortTradersHasProfit": true,
          "netPnl": 239314.618574
        }
      },
      "totalTraderPnl": 560601.52,
      "traderPnlLabel": "traders_winning"
    },
    {
      "timestamp": "2026-02-14T14:00:05.260Z",
      "date": "2026-02-14",
      "navPrice": 3.733636,
      "aum": 1223441691.260228,
      "jupiterApyPct": 11.55,
      "fees24h": 1295393,
      "avgDailyFees7d": 1358266,
      "realTimeFeeApyPct": 30.39,
      "traderExposure": {
        "SOL": {
          "guaranteedUsd": 19938680.883529,
          "globalShortSizes": 10813830.651486,
          "shortPnlDelta": 290010.571382,
          "shortTradersHasProfit": false,
          "netPnl": -290010.571382
        },
        "ETH": {
          "guaranteedUsd": 2990212.495113,
          "globalShortSizes": 1451751.133969,
          "shortPnlDelta": 5676.149396,
          "shortTradersHasProfit": false,
          "netPnl": -5676.149396
        },
        "WBTC": {
          "guaranteedUsd": 8428329.575252,
          "globalShortSizes": 5039318.537218,
          "shortPnlDelta": 175460.118237,
          "shortTradersHasProfit": true,
          "netPnl": 175460.118237
        }
      },
      "totalTraderPnl": -120226.6,
      "traderPnlLabel": "pool_winning"
    },
    {
      "timestamp": "2026-02-15T14:00:05.967Z",
      "date": "2026-02-15",
      "navPrice": 3.730883,
      "aum": 1223679215.127076,
      "jupiterApyPct": 11.55,
      "fees24h": 613080,
      "avgDailyFees7d": 1182532,
      "realTimeFeeApyPct": 26.45,
      "traderExposure": {
        "SOL": {
          "guaranteedUsd": 18263132.345174,
          "globalShortSizes": 10413672.513781,
          "shortPnlDelta": 86062.907871,
          "shortTradersHasProfit": false,
          "netPnl": -86062.907871
        },
        "ETH": {
          "guaranteedUsd": 1885927.283311,
          "globalShortSizes": 1176384.699819,
          "shortPnlDelta": 47707.77033,
          "shortTradersHasProfit": true,
          "netPnl": 47707.77033
        },
        "WBTC": {
          "guaranteedUsd": 7781399.481354,
          "globalShortSizes": 5263010.273101,
          "shortPnlDelta": 225364.858191,
          "shortTradersHasProfit": true,
          "netPnl": 225364.858191
        }
      },
      "totalTraderPnl": 187009.72,
      "traderPnlLabel": "traders_winning"
    },
    {
      "timestamp": "2026-02-16T14:00:06.796Z",
      "date": "2026-02-16",
      "navPrice": 3.666161,
      "aum": 1198952412.821966,
      "jupiterApyPct": 11.55,
      "fees24h": 1190032,
      "avgDailyFees7d": 1216425,
      "realTimeFeeApyPct": 27.77,
      "traderExposure": {
        "SOL": {
          "guaranteedUsd": 18207233.887033,
          "globalShortSizes": 9493151.593375,
          "shortPnlDelta": 127877.688169,
          "shortTradersHasProfit": true,
          "netPnl": 127877.688169
        },
        "ETH": {
          "guaranteedUsd": 2348433.265032,
          "globalShortSizes": 1055082.805358,
          "shortPnlDelta": 48744.915777,
          "shortTradersHasProfit": true,
          "netPnl": 48744.915777
        },
        "WBTC": {
          "guaranteedUsd": 8522589.402849,
          "globalShortSizes": 5604252.551334,
          "shortPnlDelta": 243307.538204,
          "shortTradersHasProfit": true,
          "netPnl": 243307.538204
        }
      },
      "totalTraderPnl": 419930.14,
      "traderPnlLabel": "traders_winning"
    },
    {
      "timestamp": "2026-02-17T14:00:10.831Z",
      "date": "2026-02-17",
      "navPrice": 3.683774,
      "aum": 1191076131.198784,
      "jupiterApyPct": 11.55,
      "fees24h": 1041102,
      "avgDailyFees7d": 1161225,
      "realTimeFeeApyPct": 26.69,
      "traderExposure": {
        "SOL": {
          "guaranteedUsd": 19456522.186165,
          "globalShortSizes": 13161317.186442,
          "shortPnlDelta": 50185.231734,
          "shortTradersHasProfit": true,
          "netPnl": 50185.231734
        },
        "ETH": {
          "guaranteedUsd": 2176725.97244,
          "globalShortSizes": 1498183.225373,
          "shortPnlDelta": 35938.767992,
          "shortTradersHasProfit": true,
          "netPnl": 35938.767992
        },
        "WBTC": {
          "guaranteedUsd": 8544688.59932,
          "globalShortSizes": 4433476.999677,
          "shortPnlDelta": 255088.493164,
          "shortTradersHasProfit": true,
          "netPnl": 255088.493164
        }
      },
      "totalTraderPnl": 341212.49,
      "traderPnlLabel": "traders_winning"
    },
    {
      "timestamp": "2026-02-20T03:00:05.690Z",
      "date": "2026-02-19",
      "navPrice": 3.634059,
      "aum": 1147687532.731238,
      "jupiterApyPct": 11.55,
      "fees24h": 839389,
      "avgDailyFees7d": 1054310,
      "realTimeFeeApyPct": 25.15,
      "traderExposure": {
        "SOL": {
          "guaranteedUsd": 21383310.612183,
          "globalShortSizes": 14420445.402246,
          "shortPnlDelta": 137524.919433,
          "shortTradersHasProfit": true,
          "netPnl": 137524.919433
        },
        "ETH": {
          "guaranteedUsd": 2198211.057091,
          "globalShortSizes": 1622152.762822,
          "shortPnlDelta": 39216.931399,
          "shortTradersHasProfit": true,
          "netPnl": 39216.931399
        },
        "WBTC": {
          "guaranteedUsd": 9019854.611754,
          "globalShortSizes": 5486272.835419,
          "shortPnlDelta": 269693.030526,
          "shortTradersHasProfit": true,
          "netPnl": 269693.030526
        }
      },
      "totalTraderPnl": 446434.88,
      "traderPnlLabel": "traders_winning"
    },
    {
      "timestamp": "2026-02-21T03:00:05.107Z",
      "date": "2026-02-20",
      "navPrice": 3.68129,
      "aum": 1155470934.824115,
      "jupiterApyPct": 7.27,
      "fees24h": 1195594,
      "avgDailyFees7d": 1040053,
      "realTimeFeeApyPct": 24.64,
      "traderExposure": {
        "SOL": {
          "guaranteedUsd": 18495945.293604,
          "globalShortSizes": 16133784.838726,
          "shortPnlDelta": 124318.997102,
          "shortTradersHasProfit": false,
          "netPnl": -124318.997102
        },
        "ETH": {
          "guaranteedUsd": 4494434.090719,
          "globalShortSizes": 1422162.752866,
          "shortPnlDelta": 41407.008534,
          "shortTradersHasProfit": true,
          "netPnl": 41407.008534
        },
        "WBTC": {
          "guaranteedUsd": 9158498.184506,
          "globalShortSizes": 5508389.633048,
          "shortPnlDelta": 229519.551824,
          "shortTradersHasProfit": true,
          "netPnl": 229519.551824
        }
      },
      "totalTraderPnl": 146607.56,
      "traderPnlLabel": "traders_winning"
    },
    {
      "timestamp": "2026-02-22T03:00:05.925Z",
      "date": "2026-02-21",
      "navPrice": 3.684499,
      "aum": 1157771059.754402,
      "jupiterApyPct": 7.27,
      "fees24h": 639191,
      "avgDailyFees7d": 1043783,
      "realTimeFeeApyPct": 24.68,
      "traderExposure": {
        "SOL": {
          "guaranteedUsd": 22852028.105474,
          "globalShortSizes": 14494477.498158,
          "shortPnlDelta": 47916.451871,
          "shortTradersHasProfit": false,
          "netPnl": -47916.451871
        },
        "ETH": {
          "guaranteedUsd": 3445984.596481,
          "globalShortSizes": 1712416.081591,
          "shortPnlDelta": 41341.281573,
          "shortTradersHasProfit": true,
          "netPnl": 41341.281573
        },
        "WBTC": {
          "guaranteedUsd": 8815691.556629,
          "globalShortSizes": 5615539.851548,
          "shortPnlDelta": 249594.270404,
          "shortTradersHasProfit": true,
          "netPnl": 249594.270404
        }
      },
      "totalTraderPnl": 243019.1,
      "traderPnlLabel": "traders_winning"
    },
    {
      "timestamp": "2026-02-23T03:00:08.520Z",
      "date": "2026-02-22",
      "navPrice": 3.504778,
      "aum": 1098241584.229838,
      "jupiterApyPct": 7.27,
      "fees24h": 645740,
      "avgDailyFees7d": 966027,
      "realTimeFeeApyPct": 24.08,
      "traderExposure": {
        "SOL": {
          "guaranteedUsd": 22653446.859224,
          "globalShortSizes": 11508975.524165,
          "shortPnlDelta": 788358.312785,
          "shortTradersHasProfit": true,
          "netPnl": 788358.312785
        },
        "ETH": {
          "guaranteedUsd": 2417282.115187,
          "globalShortSizes": 1089269.10731,
          "shortPnlDelta": 74461.27031,
          "shortTradersHasProfit": true,
          "netPnl": 74461.27031
        },
        "WBTC": {
          "guaranteedUsd": 10948883.95136,
          "globalShortSizes": 5029434.504254,
          "shortPnlDelta": 429644.973519,
          "shortTradersHasProfit": true,
          "netPnl": 429644.973519
        }
      },
      "totalTraderPnl": 1292464.56,
      "traderPnlLabel": "traders_winning"
    },
    {
      "timestamp": "2026-02-24T03:00:05.332Z",
      "date": "2026-02-23",
      "navPrice": 3.493493,
      "aum": 1089892378.058776,
      "jupiterApyPct": 7.27,
      "fees24h": 1750173,
      "avgDailyFees7d": 1067323,
      "realTimeFeeApyPct": 26.81,
      "traderExposure": {
        "SOL": {
          "guaranteedUsd": 20159796.60599,
          "globalShortSizes": 11168213.879368,
          "shortPnlDelta": 692026.513948,
          "shortTradersHasProfit": true,
          "netPnl": 692026.513948
        },
        "ETH": {
          "guaranteedUsd": 2610957.934482,
          "globalShortSizes": 1232719.195631,
          "shortPnlDelta": 74538.386241,
          "shortTradersHasProfit": true,
          "netPnl": 74538.386241
        },
        "WBTC": {
          "guaranteedUsd": 12142550.471107,
          "globalShortSizes": 7320766.789181,
          "shortPnlDelta": 446915.275148,
          "shortTradersHasProfit": true,
          "netPnl": 446915.275148
        }
      },
      "totalTraderPnl": 1213480.18,
      "traderPnlLabel": "traders_winning"
    },
    {
      "timestamp": "2026-02-25T20:49:42.274Z",
      "date": "2026-02-25",
      "navPrice": 3.815907,
      "aum": 1164521537.681598,
      "jupiterApyPct": 7.27,
      "fees24h": 1290611,
      "avgDailyFees7d": 1091698,
      "realTimeFeeApyPct": 25.66,
      "traderExposure": {
        "SOL": {
          "guaranteedUsd": 23214126.998605,
          "globalShortSizes": 19460963.596284,
          "shortPnlDelta": 878040.282723,
          "shortTradersHasProfit": false,
          "netPnl": -878040.282723
        },
        "ETH": {
          "guaranteedUsd": 2576357.484931,
          "globalShortSizes": 1672111.02933,
          "shortPnlDelta": 12728.51267,
          "shortTradersHasProfit": false,
          "netPnl": -12728.51267
        },
        "WBTC": {
          "guaranteedUsd": 9035540.974288,
          "globalShortSizes": 8212685.373962,
          "shortPnlDelta": 47999.141599,
          "shortTradersHasProfit": true,
          "netPnl": 47999.141599
        }
      },
      "totalTraderPnl": -842769.65,
      "traderPnlLabel": "pool_winning"
    },
    {
      "timestamp": "2026-02-26T14:00:08.513Z",
      "date": "2026-02-26",
      "navPrice": 3.759503,
      "aum": 1134172350.89364,
      "jupiterApyPct": 7.27,
      "fees24h": 2638815,
      "avgDailyFees7d": 1285645,
      "realTimeFeeApyPct": 31.03,
      "traderExposure": {
        "SOL": {
          "guaranteedUsd": 19317815.894893,
          "globalShortSizes": 14192142.0099,
          "shortPnlDelta": 209302.280371,
          "shortTradersHasProfit": false,
          "netPnl": -209302.280371
        },
        "ETH": {
          "guaranteedUsd": 3317896.635714,
          "globalShortSizes": 1601815.149578,
          "shortPnlDelta": 15453.726254,
          "shortTradersHasProfit": true,
          "netPnl": 15453.726254
        },
        "WBTC": {
          "guaranteedUsd": 10090806.812937,
          "globalShortSizes": 7552396.032552,
          "shortPnlDelta": 185796.142567,
          "shortTradersHasProfit": true,
          "netPnl": 185796.142567
        }
      },
      "totalTraderPnl": -8052.41,
      "traderPnlLabel": "pool_winning"
    },
    {
      "timestamp": "2026-03-05T19:52:41.887Z",
      "date": "2026-03-05",
      "navPrice": 3.82072,
      "aum": 1151629545.37949,
      "jupiterApyPct": 8.86,
      "fees24h": 2300220,
      "avgDailyFees7d": 1400852,
      "realTimeFeeApyPct": 33.3,
      "traderExposure": {
        "SOL": {
          "guaranteedUsd": 20198318.310556,
          "globalShortSizes": 16206959.815665,
          "shortPnlDelta": 492189.533439,
          "shortTradersHasProfit": false,
          "netPnl": -492189.533439
        },
        "ETH": {
          "guaranteedUsd": 3395596.672812,
          "globalShortSizes": 1606429.945215,
          "shortPnlDelta": 16074.799688,
          "shortTradersHasProfit": true,
          "netPnl": 16074.799688
        },
        "WBTC": {
          "guaranteedUsd": 8544514.348203,
          "globalShortSizes": 10395548.801951,
          "shortPnlDelta": 56302.625297,
          "shortTradersHasProfit": true,
          "netPnl": 56302.625297
        }
      },
      "totalTraderPnl": -419812.11,
      "traderPnlLabel": "pool_winning"
    },
    {
      "timestamp": "2026-03-06T14:00:50.218Z",
      "date": "2026-03-06",
      "navPrice": 3.732945,
      "aum": 1122780940.978442,
      "jupiterApyPct": 8.86,
      "fees24h": 478020,
      "avgDailyFees7d": 1325324,
      "realTimeFeeApyPct": 32.31,
      "traderExposure": {
        "SOL": {
          "guaranteedUsd": 19308583.838074,
          "globalShortSizes": 15453896.116609,
          "shortPnlDelta": 5331.510719,
          "shortTradersHasProfit": true,
          "netPnl": 5331.510719
        },
        "ETH": {
          "guaranteedUsd": 2254802.014146,
          "globalShortSizes": 2270738.235136,
          "shortPnlDelta": 77245.094605,
          "shortTradersHasProfit": true,
          "netPnl": 77245.094605
        },
        "WBTC": {
          "guaranteedUsd": 8154390.503122,
          "globalShortSizes": 9941888.345463,
          "shortPnlDelta": 311231.556239,
          "shortTradersHasProfit": true,
          "netPnl": 311231.556239
        }
      },
      "totalTraderPnl": 393808.16,
      "traderPnlLabel": "traders_winning"
    },
    {
      "timestamp": "2026-03-07T14:00:07.716Z",
      "date": "2026-03-07",
      "navPrice": 3.69377,
      "aum": 1112034734.570423,
      "jupiterApyPct": 12.44,
      "fees24h": 1326057,
      "avgDailyFees7d": 1342637,
      "realTimeFeeApyPct": 33.05,
      "traderExposure": {
        "SOL": {
          "guaranteedUsd": 19799046.342512,
          "globalShortSizes": 14565050.642965,
          "shortPnlDelta": 53707.897322,
          "shortTradersHasProfit": true,
          "netPnl": 53707.897322
        },
        "ETH": {
          "guaranteedUsd": 4432256.638383,
          "globalShortSizes": 2299830.016891,
          "shortPnlDelta": 58875.517608,
          "shortTradersHasProfit": true,
          "netPnl": 58875.517608
        },
        "WBTC": {
          "guaranteedUsd": 10091195.557281,
          "globalShortSizes": 9860492.043685,
          "shortPnlDelta": 362993.814513,
          "shortTradersHasProfit": true,
          "netPnl": 362993.814513
        }
      },
      "totalTraderPnl": 475577.23,
      "traderPnlLabel": "traders_winning"
    },
    {
      "timestamp": "2026-03-08T13:05:28.073Z",
      "date": "2026-03-08",
      "navPrice": 3.642649,
      "aum": 1096675950.384648,
      "jupiterApyPct": 12.44,
      "fees24h": 467847,
      "avgDailyFees7d": 1237538,
      "realTimeFeeApyPct": 30.89,
      "traderExposure": {
        "SOL": {
          "guaranteedUsd": 21069876.71243,
          "globalShortSizes": 13555864.851837,
          "shortPnlDelta": 511711.761795,
          "shortTradersHasProfit": true,
          "netPnl": 511711.761795
        },
        "ETH": {
          "guaranteedUsd": 2938053.20506,
          "globalShortSizes": 1776014.060818,
          "shortPnlDelta": 89468.044823,
          "shortTradersHasProfit": true,
          "netPnl": 89468.044823
        },
        "WBTC": {
          "guaranteedUsd": 11260087.646741,
          "globalShortSizes": 10319988.206936,
          "shortPnlDelta": 433322.64917,
          "shortTradersHasProfit": true,
          "netPnl": 433322.64917
        }
      },
      "totalTraderPnl": 1034502.46,
      "traderPnlLabel": "traders_winning"
    },
    {
      "timestamp": "2026-03-09T13:11:25.507Z",
      "date": "2026-03-09",
      "navPrice": 3.705575,
      "aum": 1115247799.461287,
      "jupiterApyPct": 12.44,
      "fees24h": 628920,
      "avgDailyFees7d": 1181370,
      "realTimeFeeApyPct": 29,
      "traderExposure": {
        "SOL": {
          "guaranteedUsd": 22293196.550497,
          "globalShortSizes": 11138631.930125,
          "shortPnlDelta": 135221.825409,
          "shortTradersHasProfit": true,
          "netPnl": 135221.825409
        },
        "ETH": {
          "guaranteedUsd": 2427613.74542,
          "globalShortSizes": 2003611.190999,
          "shortPnlDelta": 13899.943206,
          "shortTradersHasProfit": true,
          "netPnl": 13899.943206
        },
        "WBTC": {
          "guaranteedUsd": 9657175.65855,
          "globalShortSizes": 8561659.434897,
          "shortPnlDelta": 196932.08559,
          "shortTradersHasProfit": true,
          "netPnl": 196932.08559
        }
      },
      "totalTraderPnl": 346053.85,
      "traderPnlLabel": "traders_winning"
    },
    {
      "timestamp": "2026-03-10T13:11:32.280Z",
      "date": "2026-03-10",
      "navPrice": 3.784318,
      "aum": 1139101298.081945,
      "jupiterApyPct": 12.44,
      "fees24h": 1061162,
      "avgDailyFees7d": 1082012,
      "realTimeFeeApyPct": 26,
      "traderExposure": {
        "SOL": {
          "guaranteedUsd": 19701980.77778,
          "globalShortSizes": 10938459.828175,
          "shortPnlDelta": 119329.354829,
          "shortTradersHasProfit": false,
          "netPnl": -119329.354829
        },
        "ETH": {
          "guaranteedUsd": 2778556.715368,
          "globalShortSizes": 1774853.139603,
          "shortPnlDelta": 1061.61785,
          "shortTradersHasProfit": true,
          "netPnl": 1061.61785
        },
        "WBTC": {
          "guaranteedUsd": 8492027.816641,
          "globalShortSizes": 10014938.7703,
          "shortPnlDelta": 35032.948266,
          "shortTradersHasProfit": false,
          "netPnl": -35032.948266
        }
      },
      "totalTraderPnl": -153300.69,
      "traderPnlLabel": "pool_winning"
    },
    {
      "timestamp": "2026-03-12T01:27:13.843Z",
      "date": "2026-03-11",
      "navPrice": 3.763429,
      "aum": 1132688100.886075,
      "jupiterApyPct": 12.44,
      "fees24h": 1461411,
      "avgDailyFees7d": 1103377,
      "realTimeFeeApyPct": 26.67,
      "traderExposure": {
        "SOL": {
          "guaranteedUsd": 17552805.345588,
          "globalShortSizes": 15400630.522706,
          "shortPnlDelta": 18244.464344,
          "shortTradersHasProfit": false,
          "netPnl": -18244.464344
        },
        "ETH": {
          "guaranteedUsd": 3447359.290567,
          "globalShortSizes": 2335410.77077,
          "shortPnlDelta": 15032.44951,
          "shortTradersHasProfit": true,
          "netPnl": 15032.44951
        },
        "WBTC": {
          "guaranteedUsd": 7629334.384508,
          "globalShortSizes": 13405839.930632,
          "shortPnlDelta": 84569.305895,
          "shortTradersHasProfit": true,
          "netPnl": 84569.305895
        }
      },
      "totalTraderPnl": 81357.29,
      "traderPnlLabel": "traders_winning"
    },
    {
      "timestamp": "2026-03-12T13:00:07.861Z",
      "date": "2026-03-12",
      "navPrice": 3.786943,
      "aum": 1139766970.376469,
      "jupiterApyPct": 12.44,
      "fees24h": 1074158,
      "avgDailyFees7d": 928225,
      "realTimeFeeApyPct": 22.29,
      "traderExposure": {
        "SOL": {
          "guaranteedUsd": 20979661.031951,
          "globalShortSizes": 13016726.195072,
          "shortPnlDelta": 183683.279814,
          "shortTradersHasProfit": false,
          "netPnl": -183683.279814
        },
        "ETH": {
          "guaranteedUsd": 2961979.103243,
          "globalShortSizes": 2053691.447321,
          "shortPnlDelta": 769.016444,
          "shortTradersHasProfit": false,
          "netPnl": -769.016444
        },
        "WBTC": {
          "guaranteedUsd": 7883971.456411,
          "globalShortSizes": 10138132.196206,
          "shortPnlDelta": 8895.00785,
          "shortTradersHasProfit": false,
          "netPnl": -8895.00785
        }
      },
      "totalTraderPnl": -193347.3,
      "traderPnlLabel": "pool_winning"
    },
    {
      "timestamp": "2026-03-13T13:00:07.899Z",
      "date": "2026-03-13",
      "navPrice": 3.89232,
      "aum": 1171570515.864304,
      "jupiterApyPct": 12.44,
      "fees24h": 818073,
      "avgDailyFees7d": 976804,
      "realTimeFeeApyPct": 22.82,
      "traderExposure": {
        "SOL": {
          "guaranteedUsd": 18866720.334941,
          "globalShortSizes": 15201543.117869,
          "shortPnlDelta": 575670.083349,
          "shortTradersHasProfit": false,
          "netPnl": -575670.083349
        },
        "ETH": {
          "guaranteedUsd": 3424787.024859,
          "globalShortSizes": 2286288.003965,
          "shortPnlDelta": 72227.867811,
          "shortTradersHasProfit": false,
          "netPnl": -72227.867811
        },
        "WBTC": {
          "guaranteedUsd": 7778251.383042,
          "globalShortSizes": 10204568.699676,
          "shortPnlDelta": 319969.345626,
          "shortTradersHasProfit": false,
          "netPnl": -319969.345626
        }
      },
      "totalTraderPnl": -967867.3,
      "traderPnlLabel": "pool_winning"
    },
    {
      "timestamp": "2026-03-15T21:00:10.841Z",
      "date": "2026-03-15",
      "navPrice": 3.840099,
      "aum": 1157059867.804935,
      "jupiterApyPct": 7.83,
      "fees24h": 376925,
      "avgDailyFees7d": 1109497,
      "realTimeFeeApyPct": 26.25,
      "traderExposure": {
        "SOL": {
          "guaranteedUsd": 20180939.875924,
          "globalShortSizes": 15193116.185892,
          "shortPnlDelta": 281816.776869,
          "shortTradersHasProfit": false,
          "netPnl": -281816.776869
        },
        "ETH": {
          "guaranteedUsd": 3717673.776468,
          "globalShortSizes": 2309734.445404,
          "shortPnlDelta": 41373.293404,
          "shortTradersHasProfit": false,
          "netPnl": -41373.293404
        },
        "WBTC": {
          "guaranteedUsd": 11912350.532881,
          "globalShortSizes": 11563112.861003,
          "shortPnlDelta": 151054.298463,
          "shortTradersHasProfit": false,
          "netPnl": -151054.298463
        }
      },
      "totalTraderPnl": -474244.37,
      "traderPnlLabel": "pool_winning"
    },
    {
      "timestamp": "2026-03-16T21:00:07.739Z",
      "date": "2026-03-16",
      "navPrice": 4.028121,
      "aum": 1210292072.713269,
      "jupiterApyPct": 7.83,
      "fees24h": 1016049,
      "avgDailyFees7d": 1164802,
      "realTimeFeeApyPct": 26.35,
      "traderExposure": {
        "SOL": {
          "guaranteedUsd": 20293264.503181,
          "globalShortSizes": 22167251.890139,
          "shortPnlDelta": 1064489.990619,
          "shortTradersHasProfit": false,
          "netPnl": -1064489.990619
        },
        "ETH": {
          "guaranteedUsd": 3645499.05945,
          "globalShortSizes": 4032703.875036,
          "shortPnlDelta": 211128.341351,
          "shortTradersHasProfit": false,
          "netPnl": -211128.341351
        },
        "WBTC": {
          "guaranteedUsd": 8599057.184418,
          "globalShortSizes": 13392643.214065,
          "shortPnlDelta": 450497.308592,
          "shortTradersHasProfit": false,
          "netPnl": -450497.308592
        }
      },
      "totalTraderPnl": -1726115.64,
      "traderPnlLabel": "pool_winning"
    },
    {
      "timestamp": "2026-03-17T21:00:06.463Z",
      "date": "2026-03-17",
      "navPrice": 4.012603,
      "aum": 1204619029.009083,
      "jupiterApyPct": 7.83,
      "fees24h": 2306588,
      "avgDailyFees7d": 1342720,
      "realTimeFeeApyPct": 30.51,
      "traderExposure": {
        "SOL": {
          "guaranteedUsd": 20936918.752258,
          "globalShortSizes": 19841689.807833,
          "shortPnlDelta": 775733.969356,
          "shortTradersHasProfit": false,
          "netPnl": -775733.969356
        },
        "ETH": {
          "guaranteedUsd": 3661636.849348,
          "globalShortSizes": 4475048.343825,
          "shortPnlDelta": 165228.741259,
          "shortTradersHasProfit": false,
          "netPnl": -165228.741259
        },
        "WBTC": {
          "guaranteedUsd": 7436967.979242,
          "globalShortSizes": 17637668.629486,
          "shortPnlDelta": 381320.815794,
          "shortTradersHasProfit": false,
          "netPnl": -381320.815794
        }
      },
      "totalTraderPnl": -1322283.53,
      "traderPnlLabel": "pool_winning"
    },
    {
      "timestamp": "2026-03-19T21:00:07.919Z",
      "date": "2026-03-19",
      "navPrice": 3.840087,
      "aum": 1153929365.344886,
      "jupiterApyPct": 7.83,
      "fees24h": 1272179,
      "avgDailyFees7d": 1292094,
      "realTimeFeeApyPct": 30.65,
      "traderExposure": {
        "SOL": {
          "guaranteedUsd": 24261943.338661,
          "globalShortSizes": 16746840.698293,
          "shortPnlDelta": 15624.828605,
          "shortTradersHasProfit": true,
          "netPnl": 15624.828605
        },
        "ETH": {
          "guaranteedUsd": 3629798.637005,
          "globalShortSizes": 4607014.104951,
          "shortPnlDelta": 1502.622755,
          "shortTradersHasProfit": true,
          "netPnl": 1502.622755
        },
        "WBTC": {
          "guaranteedUsd": 10462098.510678,
          "globalShortSizes": 9642385.130578,
          "shortPnlDelta": 65879.548057,
          "shortTradersHasProfit": true,
          "netPnl": 65879.548057
        }
      },
      "totalTraderPnl": 83007,
      "traderPnlLabel": "traders_winning"
    },
    {
      "timestamp": "2026-03-20T21:00:10.667Z",
      "date": "2026-03-20",
      "navPrice": 3.835042,
      "aum": 1149365858.371975,
      "jupiterApyPct": 8.88,
      "fees24h": 1148796,
      "avgDailyFees7d": 1339340,
      "realTimeFeeApyPct": 31.9,
      "traderExposure": {
        "SOL": {
          "guaranteedUsd": 23863067.992426,
          "globalShortSizes": 16307019.705212,
          "shortPnlDelta": 2326.713364,
          "shortTradersHasProfit": false,
          "netPnl": -2326.713364
        },
        "ETH": {
          "guaranteedUsd": 5500053.016301,
          "globalShortSizes": 2789820.810199,
          "shortPnlDelta": 24311.966096,
          "shortTradersHasProfit": true,
          "netPnl": 24311.966096
        },
        "WBTC": {
          "guaranteedUsd": 11959071.093669,
          "globalShortSizes": 8892801.690059,
          "shortPnlDelta": 111148.543865,
          "shortTradersHasProfit": true,
          "netPnl": 111148.543865
        }
      },
      "totalTraderPnl": 133133.8,
      "traderPnlLabel": "traders_winning"
    },
    {
      "timestamp": "2026-03-21T21:00:06.133Z",
      "date": "2026-03-21",
      "navPrice": 3.864755,
      "aum": 1158170580.833464,
      "jupiterApyPct": 8.88,
      "fees24h": 536943,
      "avgDailyFees7d": 1080927,
      "realTimeFeeApyPct": 25.55,
      "traderExposure": {
        "SOL": {
          "guaranteedUsd": 22212548.641778,
          "globalShortSizes": 17168800.264597,
          "shortPnlDelta": 180694.181122,
          "shortTradersHasProfit": false,
          "netPnl": -180694.181122
        },
        "ETH": {
          "guaranteedUsd": 7298225.90346,
          "globalShortSizes": 2229830.293184,
          "shortPnlDelta": 148.224813,
          "shortTradersHasProfit": true,
          "netPnl": 148.224813
        },
        "WBTC": {
          "guaranteedUsd": 12522650.353901,
          "globalShortSizes": 8993126.827406,
          "shortPnlDelta": 61191.92735,
          "shortTradersHasProfit": true,
          "netPnl": 61191.92735
        }
      },
      "totalTraderPnl": -119354.03,
      "traderPnlLabel": "pool_winning"
    },
    {
      "timestamp": "2026-03-22T21:00:06.014Z",
      "date": "2026-03-22",
      "navPrice": 3.765605,
      "aum": 1128141172.072574,
      "jupiterApyPct": 8.88,
      "fees24h": 129982,
      "avgDailyFees7d": 875893,
      "realTimeFeeApyPct": 21.25,
      "traderExposure": {
        "SOL": {
          "guaranteedUsd": 23204091.2392,
          "globalShortSizes": 15732269.432906,
          "shortPnlDelta": 305822.038032,
          "shortTradersHasProfit": true,
          "netPnl": 305822.038032
        },
        "ETH": {
          "guaranteedUsd": 3178911.640066,
          "globalShortSizes": 2629616.715038,
          "shortPnlDelta": 95066.696526,
          "shortTradersHasProfit": true,
          "netPnl": 95066.696526
        },
        "WBTC": {
          "guaranteedUsd": 10694538.094879,
          "globalShortSizes": 8698674.246946,
          "shortPnlDelta": 287541.121666,
          "shortTradersHasProfit": true,
          "netPnl": 287541.121666
        }
      },
      "totalTraderPnl": 688429.86,
      "traderPnlLabel": "traders_winning"
    },
    {
      "timestamp": "2026-03-23T21:00:06.815Z",
      "date": "2026-03-23",
      "navPrice": 3.900802,
      "aum": 1162818515.790757,
      "jupiterApyPct": 8.88,
      "fees24h": 267935,
      "avgDailyFees7d": 283986,
      "realTimeFeeApyPct": 6.69,
      "traderExposure": {
        "SOL": {
          "guaranteedUsd": 20419895.781037,
          "globalShortSizes": 18536104.077964,
          "shortPnlDelta": 368068.888677,
          "shortTradersHasProfit": false,
          "netPnl": -368068.888677
        },
        "ETH": {
          "guaranteedUsd": 3304565.514894,
          "globalShortSizes": 2228666.734429,
          "shortPnlDelta": 12511.907903,
          "shortTradersHasProfit": false,
          "netPnl": -12511.907903
        },
        "WBTC": {
          "guaranteedUsd": 8576313.336048,
          "globalShortSizes": 10457685.317741,
          "shortPnlDelta": 25007.770393,
          "shortTradersHasProfit": false,
          "netPnl": -25007.770393
        }
      },
      "totalTraderPnl": -405588.57,
      "traderPnlLabel": "pool_winning"
    },
    {
      "timestamp": "2026-03-24T21:00:05.345Z",
      "date": "2026-03-24",
      "navPrice": 3.858502,
      "aum": 1142807971.494714,
      "jupiterApyPct": 8.88,
      "fees24h": 428175,
      "avgDailyFees7d": 274170,
      "realTimeFeeApyPct": 6.57,
      "traderExposure": {
        "SOL": {
          "guaranteedUsd": 28540555.563137,
          "globalShortSizes": 14244884.805988,
          "shortPnlDelta": 175252.335107,
          "shortTradersHasProfit": false,
          "netPnl": -175252.335107
        },
        "ETH": {
          "guaranteedUsd": 5117464.65929,
          "globalShortSizes": 3034801.667739,
          "shortPnlDelta": 27377.865141,
          "shortTradersHasProfit": false,
          "netPnl": -27377.865141
        },
        "WBTC": {
          "guaranteedUsd": 8726005.530989,
          "globalShortSizes": 7600591.754781,
          "shortPnlDelta": 53417.07894,
          "shortTradersHasProfit": true,
          "netPnl": 53417.07894
        }
      },
      "totalTraderPnl": -149213.12,
      "traderPnlLabel": "pool_winning"
    },
    {
      "timestamp": "2026-03-25T21:00:09.664Z",
      "date": "2026-03-25",
      "navPrice": 3.897329,
      "aum": 1153948083.620179,
      "jupiterApyPct": 8.88,
      "fees24h": 338215,
      "avgDailyFees7d": 282219,
      "realTimeFeeApyPct": 6.7,
      "traderExposure": {
        "SOL": {
          "guaranteedUsd": 23925978.30057,
          "globalShortSizes": 18507053.873845,
          "shortPnlDelta": 265525.452303,
          "shortTradersHasProfit": false,
          "netPnl": -265525.452303
        },
        "ETH": {
          "guaranteedUsd": 4043359.438204,
          "globalShortSizes": 3126844.261034,
          "shortPnlDelta": 40948.031849,
          "shortTradersHasProfit": false,
          "netPnl": -40948.031849
        },
        "WBTC": {
          "guaranteedUsd": 9320876.936523,
          "globalShortSizes": 9002870.886022,
          "shortPnlDelta": 24712.612326,
          "shortTradersHasProfit": false,
          "netPnl": -24712.612326
        }
      },
      "totalTraderPnl": -331186.1,
      "traderPnlLabel": "pool_winning"
    },
    {
      "timestamp": "2026-03-26T21:00:06.272Z",
      "date": "2026-03-26",
      "navPrice": 3.768655,
      "aum": 1111055663.218206,
      "jupiterApyPct": 8.88,
      "fees24h": 210294,
      "avgDailyFees7d": 267435,
      "realTimeFeeApyPct": 6.59,
      "traderExposure": {
        "SOL": {
          "guaranteedUsd": 33081440.681063,
          "globalShortSizes": 10030030.037241,
          "shortPnlDelta": 233988.286868,
          "shortTradersHasProfit": true,
          "netPnl": 233988.286868
        },
        "ETH": {
          "guaranteedUsd": 3793437.135266,
          "globalShortSizes": 1866233.85726,
          "shortPnlDelta": 55579.700629,
          "shortTradersHasProfit": true,
          "netPnl": 55579.700629
        },
        "WBTC": {
          "guaranteedUsd": 10384813.328533,
          "globalShortSizes": 8346119.732485,
          "shortPnlDelta": 174240.412401,
          "shortTradersHasProfit": true,
          "netPnl": 174240.412401
        }
      },
      "totalTraderPnl": 463808.4,
      "traderPnlLabel": "traders_winning"
    },
    {
      "timestamp": "2026-03-27T21:00:07.127Z",
      "date": "2026-03-27",
      "navPrice": 3.665129,
      "aum": 1080576521.227302,
      "jupiterApyPct": 9.55,
      "fees24h": 318914,
      "avgDailyFees7d": 272165,
      "realTimeFeeApyPct": 6.89,
      "traderExposure": {
        "SOL": {
          "guaranteedUsd": 28876497.927648,
          "globalShortSizes": 13890910.124302,
          "shortPnlDelta": 513887.216593,
          "shortTradersHasProfit": true,
          "netPnl": 513887.216593
        },
        "ETH": {
          "guaranteedUsd": 3836628.760531,
          "globalShortSizes": 1363658.086913,
          "shortPnlDelta": 88204.048195,
          "shortTradersHasProfit": true,
          "netPnl": 88204.048195
        },
        "WBTC": {
          "guaranteedUsd": 13964468.899016,
          "globalShortSizes": 7939251.521908,
          "shortPnlDelta": 379022.677872,
          "shortTradersHasProfit": true,
          "netPnl": 379022.677872
        }
      },
      "totalTraderPnl": 981113.94,
      "traderPnlLabel": "traders_winning"
    },
    {
      "timestamp": "2026-03-28T21:00:06.149Z",
      "date": "2026-03-28",
      "navPrice": 3.691011,
      "aum": 1088062863.081602,
      "jupiterApyPct": 9.55,
      "fees24h": 376418,
      "avgDailyFees7d": 295705,
      "realTimeFeeApyPct": 7.44,
      "traderExposure": {
        "SOL": {
          "guaranteedUsd": 35681349.71511,
          "globalShortSizes": 11354462.780865,
          "shortPnlDelta": 426919.224746,
          "shortTradersHasProfit": true,
          "netPnl": 426919.224746
        },
        "ETH": {
          "guaranteedUsd": 5415660.515458,
          "globalShortSizes": 1766936.659301,
          "shortPnlDelta": 61608.842451,
          "shortTradersHasProfit": true,
          "netPnl": 61608.842451
        },
        "WBTC": {
          "guaranteedUsd": 13228924.879102,
          "globalShortSizes": 9052325.444068,
          "shortPnlDelta": 272424.702633,
          "shortTradersHasProfit": true,
          "netPnl": 272424.702633
        }
      },
      "totalTraderPnl": 760952.77,
      "traderPnlLabel": "traders_winning"
    },
    {
      "timestamp": "2026-03-29T21:00:08.088Z",
      "date": "2026-03-29",
      "navPrice": 3.657267,
      "aum": 1078033177.772071,
      "jupiterApyPct": 9.55,
      "fees24h": 270132,
      "avgDailyFees7d": 315726,
      "realTimeFeeApyPct": 8.02,
      "traderExposure": {
        "SOL": {
          "guaranteedUsd": 28904542.953394,
          "globalShortSizes": 14312252.594594,
          "shortPnlDelta": 557630.642629,
          "shortTradersHasProfit": true,
          "netPnl": 557630.642629
        },
        "ETH": {
          "guaranteedUsd": 4934864.103004,
          "globalShortSizes": 2621940.635885,
          "shortPnlDelta": 73125.995061,
          "shortTradersHasProfit": true,
          "netPnl": 73125.995061
        },
        "WBTC": {
          "guaranteedUsd": 11956385.595624,
          "globalShortSizes": 10331695.497993,
          "shortPnlDelta": 306881.892344,
          "shortTradersHasProfit": true,
          "netPnl": 306881.892344
        }
      },
      "totalTraderPnl": 937638.53,
      "traderPnlLabel": "traders_winning"
    },
    {
      "timestamp": "2026-03-30T21:00:06.799Z",
      "date": "2026-03-30",
      "navPrice": 3.680511,
      "aum": 1081086566.850162,
      "jupiterApyPct": 9.55,
      "fees24h": 277352,
      "avgDailyFees7d": 317071,
      "realTimeFeeApyPct": 8.03,
      "traderExposure": {
        "SOL": {
          "guaranteedUsd": 28001785.913308,
          "globalShortSizes": 12065469.933956,
          "shortPnlDelta": 443285.778016,
          "shortTradersHasProfit": true,
          "netPnl": 443285.778016
        },
        "ETH": {
          "guaranteedUsd": 4986982.373485,
          "globalShortSizes": 2413694.969118,
          "shortPnlDelta": 78776.261363,
          "shortTradersHasProfit": true,
          "netPnl": 78776.261363
        },
        "WBTC": {
          "guaranteedUsd": 11112753.572824,
          "globalShortSizes": 13433694.526159,
          "shortPnlDelta": 384760.58112,
          "shortTradersHasProfit": true,
          "netPnl": 384760.58112
        }
      },
      "totalTraderPnl": 906822.62,
      "traderPnlLabel": "traders_winning"
    },
    {
      "timestamp": "2026-04-01T21:12:19.456Z",
      "date": "2026-04-01",
      "navPrice": 3.717324,
      "aum": 919884600.748522,
      "jupiterApyPct": 9.55,
      "fees24h": 586458,
      "avgDailyFees7d": 370395,
      "realTimeFeeApyPct": 11.02,
      "traderExposure": {
        "SOL": {
          "guaranteedUsd": 31596421.787848,
          "globalShortSizes": 9418733.085061,
          "shortPnlDelta": 446573.783826,
          "shortTradersHasProfit": true,
          "netPnl": 446573.783826
        },
        "ETH": {
          "guaranteedUsd": 3948883.277488,
          "globalShortSizes": 2969973.850422,
          "shortPnlDelta": 57284.46981,
          "shortTradersHasProfit": false,
          "netPnl": -57284.46981
        },
        "WBTC": {
          "guaranteedUsd": 13695983.709036,
          "globalShortSizes": 15374079.923907,
          "shortPnlDelta": 64093.226793,
          "shortTradersHasProfit": true,
          "netPnl": 64093.226793
        }
      },
      "totalTraderPnl": 453382.54,
      "traderPnlLabel": "traders_winning"
    }
  ],
  "lastUpdated": "2026-04-01T21:12:19.456Z"
}